gnsentiment/__init__.py
gnsentiment/core.py
gnsentiment-0.0.1.dist-info/LICENSE
gnsentiment-0.0.1.dist-info/METADATA
gnsentiment-0.0.1.dist-info/WHEEL
gnsentiment-0.0.1.dist-info/top_level.txt
gnsentiment-0.0.1.dist-info/RECORD
